CHANGES.txt
LICENSE.txt
MANIFEST.in
README.rst
setup.py
describe/__init__.py
describe/frozen_dict.py
describe/main.py
describe/mixins.py
describe/nose_plugin.py
describe/spec.py
describe/tracebacks.py
describe/utils.py
describe.egg-info/PKG-INFO
describe.egg-info/SOURCES.txt
describe.egg-info/dependency_links.txt
describe.egg-info/entry_points.txt
describe.egg-info/requires.txt
describe.egg-info/top_level.txt
describe/mock/__init__.py
describe/mock/args_filter.py
describe/mock/args_matcher.py
describe/mock/new_mock.py
describe/mock/repository.py
describe/mock/utils.py
describe/value/__init__.py
describe/value/builtin_values.py
describe/value/change_value.py
describe/value/decorators.py
describe/value/mixins.py
describe/value/number_value.py
describe/value/properties.py
describe/value/values.py
tests/__init__.py
tests/bowling.py
tests/crypto_problem.py
tests/test_args_matcher.py
tests/test_bowling.py
tests/test_crypto_problem.py
tests/test_example.py
tests/test_exceptions.py
tests/test_expectation_errors.py
tests/test_mixins.py
tests/test_new_mock.py
tests/utils.py