Metadata-Version: 1.0
Name: describe
Version: 0.1.2
Summary: An experimental behavioral framework inspired from rspec.
Home-page: http://github.com/jeffh/describe/
Author: Jeff Hui
Author-email: contrib@jeffhui.net
License: MIT
Platform: UNKNOWN
Classifier: Development Status :: 3 - Alpha
Classifier: Intended Audience :: Developers
Classifier: License :: OSI Approved :: MIT License
Classifier: Operating System :: OS Independent
Classifier: Programming Language :: Python
Classifier: Topic :: Software Development :: Testing
Classifier: Topic :: Software Development :: Libraries
